unikit/__init__.py
unikit/abstract.py
unikit/contrib/__init__.py
unikit/contrib/celery/__init__.py
unikit/contrib/celery/di.py
unikit/contrib/django/__init__.py
unikit/contrib/django/common.py
unikit/contrib/django/di/__init__.py
unikit/contrib/django/di/_injection.py
unikit/contrib/django/di/admin_site.py
unikit/contrib/django/di/apps.py
unikit/contrib/django/di/base.py
unikit/contrib/django/di/middleware.py
unikit/contrib/django/taskiq/__init__.py
unikit/contrib/django/taskiq/apps.py
unikit/contrib/django/taskiq/di_context.py
unikit/contrib/django/taskiq/management/__init__.py
unikit/contrib/django/taskiq/management/base.py
unikit/contrib/django/taskiq/management/commands/__init__.py
unikit/contrib/django/taskiq/management/commands/scheduler.py
unikit/contrib/django/taskiq/management/commands/workers.py
unikit/contrib/redis/__init__.py
unikit/contrib/redis/lock/__init__.py
unikit/contrib/redis/lock/async_.py
unikit/contrib/redis/lock/base.py
unikit/contrib/redis/lock/dto.py
unikit/contrib/redis/lock/sync.py
unikit/contrib/redis/lock/test.py
unikit/contrib/taskiq/__init__.py
unikit/contrib/taskiq/di.py
unikit/contrib/taskiq/dto.py
unikit/contrib/taskiq/middleware.py
unikit/contrib/taskiq/otlp.py
unikit/contrib/taskiq/progress.py
unikit/contrib/taskiq/service.py
unikit/di.py
unikit/dto/__init__.py
unikit/dto/interfaces.py
unikit/lock/__init__.py
unikit/lock/dto.py
unikit/lock/noop.py
unikit/lock/service.py
unikit/progress.py
unikit/py.typed
unikit/registry.py
unikit/security_context.py
unikit/utils/__init__.py
unikit/utils/async_utils.py
unikit/utils/default.py
unikit/utils/dict_utils.py
unikit/utils/file_utils.py
unikit/utils/list_utils.py
unikit/utils/logger.py
unikit/utils/otlp_utils.py
unikit/utils/parse_utils.py
unikit/utils/stats_utils.py
unikit/utils/stream_utils.py
unikit/utils/text_utils.py
unikit/utils/time_utils.py
unikit/utils/type_utils.py
unikit/worker.py
unikit-1.2.0.dist-info/LICENSE
unikit-1.2.0.dist-info/METADATA
unikit-1.2.0.dist-info/WHEEL
unikit-1.2.0.dist-info/RECORD
